properprot_api/__init__.py
properprot_api/client.py
properprot_api/endpoints.py
properprot_api/exceptions.py
properprot_api/models.py
properprot_client-0.1.1.dist-info/licenses/LICENSE
properprot_client-0.1.1.dist-info/METADATA
properprot_client-0.1.1.dist-info/WHEEL
properprot_client-0.1.1.dist-info/top_level.txt
properprot_client-0.1.1.dist-info/RECORD
